tangram_system/SystemWidget.vue
tangram_system/__init__.py
tangram_system/index.ts
tangram_system/dist-frontend/index.css
tangram_system/dist-frontend/index.js
tangram_system/dist-frontend/index.js.map
tangram_system/dist-frontend/plugin.json
tangram_system/package.json
tangram_system-0.2.1.dist-info/METADATA
tangram_system-0.2.1.dist-info/WHEEL
tangram_system-0.2.1.dist-info/entry_points.txt
tangram_system-0.2.1.dist-info/RECORD
