Metadata-Version: 2.4
Name: tangram_system
Version: 0.2.1
Summary: System monitoring plugin for tangram
Author-email: Xavier Olive <git@xoolive.org>, Junzi Sun <git@junzis.com>
License-Expression: AGPL-3.0
Classifier: Development Status :: 4 - Beta
Classifier: Intended Audience :: Science/Research
Classifier: License :: OSI Approved :: GNU Affero General Public License v3
Classifier: Programming Language :: Python :: 3
Classifier: Programming Language :: Python :: 3.10
Classifier: Programming Language :: Python :: 3.11
Classifier: Programming Language :: Python :: 3.12
Classifier: Programming Language :: Python :: 3.13
Classifier: Programming Language :: Python :: 3.14
Classifier: Topic :: System :: Monitoring
Requires-Python: >=3.10
Requires-Dist: psutil
Requires-Dist: tangram-core>=0.2.0
